foremon/__init__.py
foremon/__main__.py
foremon/app.py
foremon/cli.py
foremon/config.py
foremon/debounce.py
foremon/display.py
foremon/errors.py
foremon/monitor.py
foremon/queue.py
foremon/task.py
foremon/util.py
foremon-1.3.0.dist-info/LICENSE.txt
foremon-1.3.0.dist-info/METADATA
foremon-1.3.0.dist-info/WHEEL
foremon-1.3.0.dist-info/entry_points.txt
foremon-1.3.0.dist-info/top_level.txt
foremon-1.3.0.dist-info/RECORD
