Metadata-Version: 2.1
Name: foremon
Version: 1.3.0
Summary: Automatically restart applications when file changes are detected.
Home-page: http://github.com/matutter/foremon
Author: Mathew Utter
Author-email: mcutter.svc@gmail.com
License: MIT
Keywords: python filesystem monitoring scripting task automation
Platform: UNKNOWN
Classifier: Development Status :: 5 - Production/Stable
Classifier: Environment :: Console
Classifier: Intended Audience :: Developers
Classifier: License :: OSI Approved :: MIT License
Classifier: Natural Language :: English
Classifier: Operating System :: POSIX :: Linux
Classifier: Operating System :: MacOS :: MacOS X
Classifier: Operating System :: POSIX :: BSD
Classifier: Operating System :: Microsoft :: Windows :: Windows Vista
Classifier: Operating System :: Microsoft :: Windows :: Windows 7
Classifier: Operating System :: Microsoft :: Windows :: Windows 8
Classifier: Operating System :: Microsoft :: Windows :: Windows 8.1
Classifier: Operating System :: Microsoft :: Windows :: Windows 10
Classifier: Operating System :: OS Independent
Classifier: Programming Language :: Python
Classifier: Programming Language :: Python :: 3
Classifier: Programming Language :: Python :: 3 :: Only
Classifier: Programming Language :: Python :: 3.6
Classifier: Programming Language :: Python :: 3.7
Classifier: Programming Language :: Python :: 3.8
Classifier: Programming Language :: Python :: 3.9
Classifier: Topic :: Software Development :: Build Tools
Classifier: Topic :: Software Development :: Libraries
Classifier: Topic :: System :: Filesystems
Classifier: Topic :: System :: Monitoring
Classifier: Topic :: Utilities
Requires: ansicolors
Requires: click
Requires: watchdog
Requires: toml
Requires: pydantic
Requires-Python: >=3.6.1
Requires-Dist: ansicolors (>=1.1.8)
Requires-Dist: click (>=7.1.2)
Requires-Dist: watchdog (>=1.0.2)
Requires-Dist: toml (>=0.10.2)
Requires-Dist: pydantic (>=1.7.3)
